<?xml version="1.0" encoding="utf-8" ?><dwsync><file name="1.jpg" server="www6.semo.edu//anime_party/" local="3522331048" remote="3522369780" Dst="-1" /><file name="10.jpg" server="www6.semo.edu//anime_party/" local="3522332806" remote="3522369780" Dst="-1" /><file name="10_thumbnail.jpg" server="www6.semo.edu//anime_party/" local="3522332822" remote="3522369780" Dst="-1" /><file name="11.jpg" server="www6.semo.edu//anime_party/" local="3522332835" remote="3522369780" Dst="-1" /><file name="11_thumbnail.jpg" server="www6.semo.edu//anime_party/" local="3522332847" remote="3522369780" Dst="-1" /><file name="12.jpg" server="www6.semo.edu//anime_party/" local="3522332859" remote="3522369780" Dst="-1" /><file name="12_thumbnail.jpg" server="www6.semo.edu//anime_party/" local="3522332870" remote="3522369780" Dst="-1" /><file name="13.jpg" server="www6.semo.edu//anime_party/" local="3522334459" remote="3522369780" Dst="-1" /><file name="13_thumbnail.jpg" server="www6.semo.edu//anime_party/" local="3522334474" remote="3522369780" Dst="-1" /><file name="14.jpg" server="www6.semo.edu//anime_party/" local="3522334488" remote="3522369840" Dst="-1" /><file name="14_thumbnail.jpg" server="www6.semo.edu//anime_party/" local="3522334503" remote="3522369840" Dst="-1" /><file name="15.jpg" server="www6.semo.edu//anime_party/" local="3522334520" remote="3522369840" Dst="-1" /><file name="15_thumbnail.jpg" server="www6.semo.edu//anime_party/" local="3522334551" remote="3522369840" Dst="-1" /><file name="16.jpg" server="www6.semo.edu//anime_party/" local="3522334695" remote="3522369840" Dst="-1" /><file name="16_thumbnail.jpg" server="www6.semo.edu//anime_party/" local="3522334712" remote="3522369840" Dst="-1" /><file name="17.jpg" server="www6.semo.edu//anime_party/" local="3522334968" remote="3522369840" Dst="-1" /><file name="17_thumbnail.jpg" server="www6.semo.edu//anime_party/" local="3522334981" remote="3522369840" Dst="-1" /><file name="18.jpg" server="www6.semo.edu//anime_party/" local="3522340061" remote="3522369840" Dst="-1" /><file name="18_thumbnail.jpg" server="www6.semo.edu//anime_party/" local="3522340086" remote="3522369840" Dst="-1" /><file name="1_thumbnail.jpg" server="www6.semo.edu//anime_party/" local="3522331066" remote="3522369840" Dst="-1" /><file name="2.jpg" server="www6.semo.edu//anime_party/" local="3522331284" remote="3522369840" Dst="-1" /><file name="2_thumbnail.jpg" server="www6.semo.edu//anime_party/" local="3522331300" remote="3522369840" Dst="-1" /><file name="3.jpg" server="www6.semo.edu//anime_party/" local="3522331598" remote="3522369840" Dst="-1" /><file name="3_thumbnail.jpg" server="www6.semo.edu//anime_party/" local="3522331624" remote="3522369840" Dst="-1" /><file name="4.jpg" server="www6.semo.edu//anime_party/" local="3522331638" remote="3522369840" Dst="-1" /><file name="4_thumbnail.jpg" server="www6.semo.edu//anime_party/" local="3522331652" remote="3522369840" Dst="-1" /><file name="5.jpg" server="www6.semo.edu//anime_party/" local="3522331773" remote="3522369840" Dst="-1" /><file name="5_thumbnail.jpg" server="www6.semo.edu//anime_party/" local="3522331787" remote="3522369840" Dst="-1" /><file name="6.jpg" server="www6.semo.edu//anime_party/" local="3522332281" remote="3522369840" Dst="-1" /><file name="6_thumbnail.jpg" server="www6.semo.edu//anime_party/" local="3522332294" remote="3522369840" Dst="-1" /><file name="7.jpg" server="www6.semo.edu//anime_party/" local="3522332307" remote="3522369840" Dst="-1" /><file name="7_thumbnail.jpg" server="www6.semo.edu//anime_party/" local="3522332322" remote="3522369840" Dst="-1" /><file name="8.jpg" server="www6.semo.edu//anime_party/" local="3522332341" remote="3522369840" Dst="-1" /><file name="8_thumbnail.jpg" server="www6.semo.edu//anime_party/" local="3522332356" remote="3522369840" Dst="-1" /><file name="9.jpg" server="www6.semo.edu//anime_party/" local="3522332778" remote="3522369840" Dst="-1" /><file name="9_thumbnail.jpg" server="www6.semo.edu//anime_party/" local="3522332792" remote="3522369840" Dst="-1" /><file name="cosplayBall2014Poster.jpg" server="www6.semo.edu//anime_party/" local="3522330133" remote="3522369840" Dst="-1" /></dwsync>